{
  "manufacturers": [
    {
      "manufacturer_id": 1,
      "name": "Windy City",
      "wires": [
        {
          "wire_type": "12-2 FPLP",
          "outer_diameter_in": ".238"
        },
        {
          "wire_type": "14-2 FPLP",
          "outer_diameter_in": ".206"
        },
        {
          "wire_type": "14-4 FPLP",
          "outer_diameter_in": ".242"
        },
        {
          "wire_type": "16-2 FPLP",
          "outer_diameter_in": ".178"
        },
        {
          "wire_type": "16-4 FPLP",
          "outer_diameter_in": ".208"
        },
        {
          "wire_type": "18-2 FPLP",
          "outer_diameter_in": ".158"
        },
        {
          "wire_type": "18-4 FPLP",
          "outer_diameter_in": ".184"
        }
      ]
    },
    {
      "manufacturer_id": 2,
      "name": "Genesis",
      "wires": [
        {
          "wire_type": "14-2 FPLP",
          "outer_diameter_in": ".206"
        },
        {
          "wire_type": "12-2 FPLP",
          "outer_diameter_in": ".228"
        },
        {
          "wire_type": "14-4 FPLP",
          "outer_diameter_in": ".230"
        },
        {
          "wire_type": "16-4 FPLP",
          "outer_diameter_in": ".201"
        },
        {
          "wire_type": "16-2 FPLP",
          "outer_diameter_in": ".177"
        },
        {
          "wire_type": "18-4 FPLP",
          "outer_diameter_in": ".157"
        },
        {
          "wire_type": "18-2 FPLP",
          "outer_diameter_in": ".136"
        }
      ]
    }
  ]
}
